pyture/__init__.py
pyture/capture.py
pyture-0.1.0.dist-info/licenses/LICENSE
pyture-0.1.0.dist-info/METADATA
pyture-0.1.0.dist-info/WHEEL
pyture-0.1.0.dist-info/top_level.txt
pyture-0.1.0.dist-info/RECORD
