Metadata-Version: 2.4
Name: pyture
Version: 0.1.0
Summary: A simple capture utility for logging variables in Python
Home-page: https://github.com/YOUR_USERNAME/pyture
Author: Shakib Sayyed
License: MIT
Classifier: Programming Language :: Python :: 3
Classifier: License :: OSI Approved :: MIT License
Classifier: Operating System :: OS Independent
Requires-Python: >=3.6
License-File: LICENSE
Dynamic: license-file
